README.md
setup.py
frasco_angular/__init__.py
frasco_angular.egg-info/PKG-INFO
frasco_angular.egg-info/SOURCES.txt
frasco_angular.egg-info/dependency_links.txt
frasco_angular.egg-info/not-zip-safe
frasco_angular.egg-info/requires.txt
frasco_angular.egg-info/top_level.txt
frasco_angular/static/angular-frasco.js
frasco_angular/templates/angular_app_layout.html
frasco_angular/templates/angular_layout.html