Metadata-Version: 1.0
Name: frasco-angular
Version: 0.7.1
Summary: Angular integration for Frasco
Home-page: http://github.com/frascoweb/frasco-angular
Author: Maxime Bouroumeau-Fuseau
Author-email: maxime.bouroumeau@gmail.com
License: MIT
Platform: any
